openguardrails/__init__.py
openguardrails/client.py
openguardrails/exceptions.py
openguardrails/models.py
openguardrails/py.typed
openguardrails-3.0.2.dist-info/licenses/LICENSE
openguardrails-3.0.2.dist-info/METADATA
openguardrails-3.0.2.dist-info/WHEEL
openguardrails-3.0.2.dist-info/top_level.txt
openguardrails-3.0.2.dist-info/RECORD
