Metadata-Version: 2.4
Name: openguardrails
Version: 3.0.2
Summary: OpenGuardrails Python SDK - An LLM-based context-aware AI guardrail that understands conversation context for security, safety and data leakage detection.
Author-email: OpenGuardrails <thomas@openguardrails.com>
Maintainer-email: OpenGuardrails <thomas@openguardrails.com>
License-Expression: Apache-2.0
Project-URL: Homepage, https://openguardrails.com
Project-URL: Documentation, https://openguardrails.com
Project-URL: Repository, https://github.com/openguardrails/openguardrails
Project-URL: Issues, https://github.com/openguardrails/openguardrails-python/issues
Project-URL: Changelog, https://github.com/openguardrails/openguardrails-python/blob/main/CHANGELOG.md
Keywords: ai,safety,guardrails,llm,content-moderation,prompt-injection,security,compliance,openguardrails
Classifier: Development Status :: 4 - Beta
Classifier: Intended Audience :: Developers
Classifier: Operating System :: OS Independent
Classifier: Programming Language :: Python :: 3
Classifier: Programming Language :: Python :: 3.8
Classifier: Programming Language :: Python :: 3.9
Classifier: Programming Language :: Python :: 3.10
Classifier: Programming Language :: Python :: 3.11
Classifier: Programming Language :: Python :: 3.12
Classifier: Topic :: Software Development :: Libraries :: Python Modules
Classifier: Topic :: Internet :: WWW/HTTP :: HTTP Servers
Classifier: Topic :: Security
Classifier: Topic :: Scientific/Engineering :: Artificial Intelligence
Requires-Python: >=3.8
License-File: LICENSE
Requires-Dist: requests>=2.25.0
Requires-Dist: aiohttp>=3.8.0
Requires-Dist: typing-extensions>=4.0.0
Requires-Dist: pydantic>=2.0.0
Provides-Extra: dev
Requires-Dist: pytest>=6.0.0; extra == "dev"
Requires-Dist: pytest-cov>=3.0.0; extra == "dev"
Requires-Dist: black>=22.0.0; extra == "dev"
Requires-Dist: isort>=5.0.0; extra == "dev"
Requires-Dist: flake8>=4.0.0; extra == "dev"
Requires-Dist: mypy>=1.0.0; extra == "dev"
Requires-Dist: types-requests; extra == "dev"
Provides-Extra: test
Requires-Dist: pytest>=6.0.0; extra == "test"
Requires-Dist: pytest-cov>=3.0.0; extra == "test"
Requires-Dist: responses>=0.18.0; extra == "test"
Dynamic: license-file
